edi_835_parser/__init__.py
edi_835_parser/elements/__init__.py
edi_835_parser/elements/adjustment_group_code.py
edi_835_parser/elements/adjustment_reason_code.py
edi_835_parser/elements/amount_qualifier.py
edi_835_parser/elements/authorization_information_qualifier.py
edi_835_parser/elements/claim_status.py
edi_835_parser/elements/date.py
edi_835_parser/elements/date_qualifier.py
edi_835_parser/elements/dollars.py
edi_835_parser/elements/entity_code.py
edi_835_parser/elements/entity_type.py
edi_835_parser/elements/identification_code_qualifier.py
edi_835_parser/elements/identifier.py
edi_835_parser/elements/integer.py
edi_835_parser/elements/organization.py
edi_835_parser/elements/organization_type.py
edi_835_parser/elements/payment_method.py
edi_835_parser/elements/reference_qualifier.py
edi_835_parser/elements/remark_code.py
edi_835_parser/elements/remark_qualifier.py
edi_835_parser/elements/service_code.py
edi_835_parser/elements/service_modifier.py
edi_835_parser/elements/service_qualifier.py
edi_835_parser/elements/utilities.py
edi_835_parser/loops/__init__.py
edi_835_parser/loops/claim.py
edi_835_parser/loops/organization.py
edi_835_parser/loops/service.py
edi_835_parser/segments/__init__.py
edi_835_parser/segments/address.py
edi_835_parser/segments/amount.py
edi_835_parser/segments/claim.py
edi_835_parser/segments/date.py
edi_835_parser/segments/entity.py
edi_835_parser/segments/financial_information.py
edi_835_parser/segments/interchange.py
edi_835_parser/segments/location.py
edi_835_parser/segments/organization.py
edi_835_parser/segments/reassociation_trace_number.py
edi_835_parser/segments/reference.py
edi_835_parser/segments/remark.py
edi_835_parser/segments/service.py
edi_835_parser/segments/service_adjustment.py
edi_835_parser/segments/utilities.py
edi_835_parser/transaction_set/__init__.py
edi_835_parser/transaction_set/transaction_set.py
edi_835_parser/transaction_set/transaction_sets.py
edi_835_parser_brewer-1.7.2.dist-info/LICENSE
edi_835_parser_brewer-1.7.2.dist-info/METADATA
edi_835_parser_brewer-1.7.2.dist-info/WHEEL
edi_835_parser_brewer-1.7.2.dist-info/RECORD
