Metadata-Version: 2.1
Name: edi-835-parser-brewer
Version: 1.7.2
Summary: A simple EDI 835 file format parser.
License: MIT
Author: Keiron Stoddart
Author-email: keiron.stoddart@gmail.com
Requires-Python: >=3.12,<4.0
Classifier: License :: OSI Approved :: MIT License
Classifier: Programming Language :: Python :: 3
Classifier: Programming Language :: Python :: 3.12
Requires-Dist: pandas (>=2.0.3,<3.0.0)
